TSL/TSLCore.py
TSL/TSLEngine.py
TSL/TSLHelpers.py
TSL/__init__.py
tsl_compiler-0.0.1.dist-info/LICENSE
tsl_compiler-0.0.1.dist-info/METADATA
tsl_compiler-0.0.1.dist-info/WHEEL
tsl_compiler-0.0.1.dist-info/top_level.txt
tsl_compiler-0.0.1.dist-info/RECORD
