Metadata-Version: 2.1
Name: tsl-compiler
Version: 0.0.1
Summary: Text Scraping Language package
Home-page: https://github.com/polygoat/TSL
Author: Dan Borufka
Author-email: danborufka@gmail.com
License: UNKNOWN
Platform: UNKNOWN
Classifier: Programming Language :: Python :: 3
Classifier: License :: OSI Approved :: MIT License
Classifier: Operating System :: OS Independent
